LICENSE
seg_text/__init__.py
seg_text/seg_text.py
seg_text-0.1.2.dist-info/LICENSE
seg_text-0.1.2.dist-info/WHEEL
seg_text-0.1.2.dist-info/METADATA
seg_text-0.1.2.dist-info/RECORD
