Metadata-Version: 2.1
Name: seg-text
Version: 0.1.2
Summary: pack_name descr 
Home-page: https://github.com/ffreemt/seg-text
License: MIT
Author: ffreemt
Requires-Python: >=3.8,<4.0
Classifier: License :: OSI Approved :: MIT License
Classifier: Programming Language :: Python :: 3
Classifier: Programming Language :: Python :: 3.10
Classifier: Programming Language :: Python :: 3.8
Classifier: Programming Language :: Python :: 3.9
Requires-Dist: Morfessor (==2.0.6)
Requires-Dist: fastlid (>=0.1.7,<0.2.0)
Requires-Dist: icecream (>=2.1.1,<3.0.0)
Requires-Dist: install (>=1.3.5,<2.0.0)
Requires-Dist: logzero (>=1.7.0,<2.0.0)
Requires-Dist: numpy (>=1.22.2,<2.0.0)
Requires-Dist: sentence-splitter (>=1.4,<2.0)
Requires-Dist: tqdm (>=4.62.3,<5.0.0)
Requires-Dist: vtext (>=0.2.0,<0.3.0)
Project-URL: Repository, https://github.com/ffreemt/seg-text
